yapy/__init__.py
yapy/compare/__init__.py
yapy/compare/file_instance.py
yapy/compare/plagiarism_compare.py
yapy/compare/output/__init__.py
yapy/compare/output/csv_formatter.py
yapy/compare/output/formatter.py
yapy/compare/output/html_formatter.py
yapy/compare/output/json_formatter.py
yapy/parser/__init__.py
yapy/parser/parser.py
yapy/parser/parser_result.py
yapy/score/__init__.py
yapy/score/similarity_score.py
yapy_arm64-1.0.dist-info/LICENSE
yapy_arm64-1.0.dist-info/METADATA
yapy_arm64-1.0.dist-info/WHEEL
yapy_arm64-1.0.dist-info/top_level.txt
yapy_arm64-1.0.dist-info/RECORD
