Metadata-Version: 2.1
Name: yapy-arm64
Version: 1.0
Summary: UNKNOWN
Home-page: UNKNOWN
Author: Luis Tavares
License: UNKNOWN
Platform: UNKNOWN
Classifier: Programming Language :: Python :: 3
Classifier: Programming Language :: Python :: 3.6
Classifier: Programming Language :: Python :: 3.7
Classifier: Programming Language :: Python :: 3.8
Classifier: License :: OSI Approved :: MIT License
Classifier: Operating System :: OS Independent
Requires-Python: >=3.6
Requires-Dist: lark (==0.11.1)
Requires-Dist: Unidecode (==1.2.0)
